langchain_openailike_llms_adapters/__init__.py
langchain_openailike_llms_adapters/adapters.py
langchain_openailike_llms_adapters/provider.py
langchain_openailike_llms_adapters/py.typed
langchain_openailike_llms_adapters/utils.py
langchain_openailike_llms_adapters-0.2.1.dist-info/METADATA
langchain_openailike_llms_adapters-0.2.1.dist-info/WHEEL
langchain_openailike_llms_adapters-0.2.1.dist-info/licenses/LICENSE
langchain_openailike_llms_adapters-0.2.1.dist-info/RECORD
