Metadata-Version: 2.4
Name: langchain-openailike-llms-adapters
Version: 0.2.1
Summary: A utils to connect to all models compatible with the OpenAI style
Project-URL: Source Code, https://github.com/TBice123123/langchain-openailike-llms-adapters
Author-email: tiebingice <tiebingice123@outlook.com>
License-File: LICENSE
Requires-Python: >=3.11
Requires-Dist: dotenv>=0.9.9
Requires-Dist: langchain-openai>=0.3.28
Requires-Dist: langchain>=0.3.26
